fexp/__init__.py
fexp/__main__.py
fexp/cli.py
fexp/server.py
fexp/template.py
fexp-0.1.0.dist-info/METADATA
fexp-0.1.0.dist-info/WHEEL
fexp-0.1.0.dist-info/entry_points.txt
fexp-0.1.0.dist-info/licenses/LICENSE
fexp-0.1.0.dist-info/RECORD
