Metadata-Version: 2.4
Name: fexp
Version: 0.1.0
Summary: A minimal CLI HTTP file explorer
Project-URL: Homepage, https://github.com/conwnet/fexp
Author-email: netcon <netcon@live.com>
License: MIT
License-File: LICENSE
Classifier: License :: OSI Approved :: MIT License
Classifier: Operating System :: OS Independent
Classifier: Programming Language :: Python :: 3
Requires-Python: >=3.8
